awslabs/__init__.py
awslabs/s3_tables_mcp_server/__init__.py
awslabs/s3_tables_mcp_server/constants.py
awslabs/s3_tables_mcp_server/database.py
awslabs/s3_tables_mcp_server/models.py
awslabs/s3_tables_mcp_server/namespaces.py
awslabs/s3_tables_mcp_server/resources.py
awslabs/s3_tables_mcp_server/s3_operations.py
awslabs/s3_tables_mcp_server/server.py
awslabs/s3_tables_mcp_server/table_buckets.py
awslabs/s3_tables_mcp_server/tables.py
awslabs/s3_tables_mcp_server/utils.py
awslabs/s3_tables_mcp_server/engines/__init__.py
awslabs/s3_tables_mcp_server/engines/pyiceberg.py
awslabs/s3_tables_mcp_server/file_processor/__init__.py
awslabs/s3_tables_mcp_server/file_processor/csv.py
awslabs/s3_tables_mcp_server/file_processor/parquet.py
awslabs/s3_tables_mcp_server/file_processor/utils.py
awslabs_s3_tables_mcp_server-0.0.17.dist-info/METADATA
awslabs_s3_tables_mcp_server-0.0.17.dist-info/WHEEL
awslabs_s3_tables_mcp_server-0.0.17.dist-info/entry_points.txt
awslabs_s3_tables_mcp_server-0.0.17.dist-info/licenses/LICENSE
awslabs_s3_tables_mcp_server-0.0.17.dist-info/licenses/NOTICE
awslabs_s3_tables_mcp_server-0.0.17.dist-info/RECORD
