Metadata-Version: 2.4
Name: awslabs.s3-tables-mcp-server
Version: 0.0.17
Summary: An AWS Labs Model Context Protocol (MCP) server for awslabs.s3-tables-mcp-server
Project-URL: homepage, https://awslabs.github.io/mcp/
Project-URL: docs, https://awslabs.github.io/mcp/servers/s3-tables-mcp-server/
Project-URL: documentation, https://awslabs.github.io/mcp/servers/s3-tables-mcp-server/
Project-URL: repository, https://github.com/awslabs/mcp.git
Project-URL: changelog, https://github.com/awslabs/mcp/blob/main/src/s3-tables-mcp-server/CHANGELOG.md
Author: Amazon Web Services
Author-email: AWSLabs MCP <203918161+awslabs-mcp@users.noreply.github.com>, Oleksandr Khomin <okhomi@amazon.com>
License: Apache-2.0
License-File: LICENSE
License-File: NOTICE
Classifier: License :: OSI Approved :: Apache Software License
Classifier: Operating System :: OS Independent
Classifier: Programming Language :: Python
Classifier: Programming Language :: Python :: 3
Classifier: Programming Language :: Python :: 3.10
Classifier: Programming Language :: Python :: 3.11
Classifier: Programming Language :: Python :: 3.12
Classifier: Programming Language :: Python :: 3.13
Requires-Python: >=3.10
Requires-Dist: boto3==1.40.8
Requires-Dist: daft==0.5.8
Requires-Dist: loguru==0.7.3
Requires-Dist: mcp[cli]==1.23.0
Requires-Dist: pyarrow==22.0.0
Requires-Dist: pydantic==2.11.0
Requires-Dist: pyiceberg==0.10.0
Requires-Dist: sqlparse==0.5.3
